nops_sink/__init__.py
nops_sink/kafka.py
nops_sink/s3.py
nops_sink/tests/__init__.py
nops_sink/tests/test_s3.py
nops_sink-0.4.0.dist-info/WHEEL
nops_sink-0.4.0.dist-info/METADATA
nops_sink-0.4.0.dist-info/RECORD
