Metadata-Version: 2.1
Name: nops-sink
Version: 0.4.0
Summary: Set of modules to simplify submission of data to the various sinks.
Author: nOps Engineers
Author-email: eng@nops.io
Classifier: Programming Language :: Python :: 2
Classifier: Programming Language :: Python :: 2.7
Classifier: Programming Language :: Python :: 3
Classifier: Programming Language :: Python :: 3.10
Classifier: Programming Language :: Python :: 3.4
Classifier: Programming Language :: Python :: 3.5
Classifier: Programming Language :: Python :: 3.6
Classifier: Programming Language :: Python :: 3.7
Classifier: Programming Language :: Python :: 3.8
Classifier: Programming Language :: Python :: 3.9
Requires-Dist: boto3 (>1.22)
Requires-Dist: msgspec (>0.7.0)
Requires-Dist: nops_kafka (>0.1)
Requires-Dist: smart_open (>4.0)
